dt_browser/__init__.py
dt_browser/bookmarks.py
dt_browser/browser.py
dt_browser/column_selector.py
dt_browser/custom_table.py
dt_browser/expression_box.py
dt_browser/filter_box.py
dt_browser/save_df_modal.py
dt_browser/suggestor.py
dt_browser-0.0.16.dist-info/licenses/LICENSE
dt_browser-0.0.16.dist-info/METADATA
dt_browser-0.0.16.dist-info/WHEEL
dt_browser-0.0.16.dist-info/entry_points.txt
dt_browser-0.0.16.dist-info/top_level.txt
dt_browser-0.0.16.dist-info/RECORD
