Metadata-Version: 2.4
Name: dt-browser
Version: 0.0.16
Summary: A TUI for browsing, searching, and filtering dataframes using Polars/Apache Arrow
Author: Kyle Kavanagh
License: MIT License
Project-URL: Homepage, https://github.com/kdkavanagh/dt-browser
Keywords: pyarrow,dataframe,tui,polars,datatable,textual
Classifier: License :: OSI Approved :: MIT License
Classifier: Programming Language :: Python
Classifier: Programming Language :: Python :: 3
Requires-Python: >=3.11
License-File: LICENSE
Requires-Dist: click
Requires-Dist: tzlocal
Requires-Dist: textual>=6.0.0
Requires-Dist: polars<2.0,>=1.36
Provides-Extra: dev
Requires-Dist: black; extra == "dev"
Requires-Dist: isort; extra == "dev"
Requires-Dist: pylint; extra == "dev"
Dynamic: license-file
